setup.py
pyexcel_render/__init__.py
pyexcel_render/excel_template.py
pyexcel_render.egg-info/PKG-INFO
pyexcel_render.egg-info/SOURCES.txt
pyexcel_render.egg-info/dependency_links.txt
pyexcel_render.egg-info/requires.txt
pyexcel_render.egg-info/top_level.txt