Metadata-Version: 1.1
Name: pyexcel_render
Version: 0.0.1.dev0
Summary: python excel template render
Home-page: http://github.com/comger/pyexcel
Author: comger@gmail.com
Author-email: comger@gmail.com
License: https://opensource.org/licenses/MIT
Keywords: python,excel,template,render,report
Platform: UNKNOWN
Classifier: License :: OSI Approved :: Apache Software License
Classifier: Programming Language :: Python :: 2
Classifier: Programming Language :: Python :: 2.6
Classifier: Programming Language :: Python :: 2.7
Classifier: Programming Language :: Python :: Implementation :: CPython
Classifier: Programming Language :: Python :: Implementation :: PyPy
